rollon/__init__.py
rollon/__main__.py
rollon/config.py
rollon/core.py
rollon/downloader.py
rollon/itunes.py
rollon/menu.py
rollon/tags.py
rollon/ui.py
rollon/utils.py
rollon-0.1.7.dist-info/METADATA
rollon-0.1.7.dist-info/WHEEL
rollon-0.1.7.dist-info/entry_points.txt
rollon-0.1.7.dist-info/top_level.txt
rollon-0.1.7.dist-info/RECORD
