Metadata-Version: 2.4
Name: rollon
Version: 0.1.7
Summary: Roll-On: Descargas con yt-dlp, UI limpia y portada Apple para OPUS (menú interactivo).
Home-page: https://github.com/Cesarx9/Roll-On
Author: Cesarx9
License: MIT
Requires-Python: >=3.7
Requires-Dist: yt-dlp>=2025.1.0; python_version >= "3.8"
Dynamic: home-page
Dynamic: requires-python
